a2f_client/__init__.py
a2f_client/a2f_client.py
a2f_client/assets/mark_arkit_solved_default.usd
a2f_client/assets/mark_arkit_solved_streaming.usd
a2f_client/example_usage.py
a2f_client/modules/_a2f_endpoints_client.py
a2f_client/modules/_a2f_http_client.py
a2f_client/samples/sample-0.wav
a2f_client/samples/sample-1.wav
a2f_client/settings.py
a2f_client/tests/test_blendshapes.py
a2f_client/utils.py
a2f_client-0.1.3.dist-info/LICENSE
a2f_client-0.1.3.dist-info/METADATA
a2f_client-0.1.3.dist-info/WHEEL
a2f_client-0.1.3.dist-info/RECORD
