Metadata-Version: 2.3
Name: a2f-client
Version: 0.1.3
Summary: 
Author: Alex Thillen
Author-email: alexthillen852@gmail.com
Requires-Python: >=3.10,<4.0
Classifier: Programming Language :: Python :: 3
Classifier: Programming Language :: Python :: 3.10
Classifier: Programming Language :: Python :: 3.11
Classifier: Programming Language :: Python :: 3.12
Classifier: Programming Language :: Python :: 3.13
Requires-Dist: flask (>=3.1.0,<4.0.0)
Requires-Dist: librosa (>=0.11.0,<0.12.0)
Requires-Dist: loguru (>=0.7.3,<0.8.0)
Requires-Dist: requests (>=2.32.3,<3.0.0)
Requires-Dist: wavfile (>=4.7.2,<5.0.0)
